Metadata-Version: 2.1
Name: aioHelloWorld
Version: 0.3a0.post0
Summary: This is a asynchronous package for printing hello world
Home-page: UNKNOWN
Author: Exainz
License: UNKNOWN
Project-URL: Issue tracker, https://github.com/Exainz/aioHelloWorld/issues
Platform: UNKNOWN
